quant_clone/__init__.py
quant_clone/main.py
quant_clone-0.1.1.dist-info/licenses/LICENSE
quant_clone-0.1.1.dist-info/METADATA
quant_clone-0.1.1.dist-info/WHEEL
quant_clone-0.1.1.dist-info/entry_points.txt
quant_clone-0.1.1.dist-info/top_level.txt
quant_clone-0.1.1.dist-info/RECORD
