Metadata-Version: 2.4
Name: quant_clone
Version: 0.1.1
Summary: Generate a llama-quantize command to copy the quantization parameters of any GGUF
Author: electroglyph
License-Expression: BSD-2-Clause
Project-URL: Homepage, https://github.com/electroglyph/quant_clone
Project-URL: Repository, https://github.com/electroglyph/quant_clone
Classifier: Programming Language :: Python :: 3
Classifier: Operating System :: OS Independent
Requires-Python: >=3.8
License-File: LICENSE
Requires-Dist: gguf
Dynamic: license-file
